django_factories.py
pytest_django_factories-0.2.3.dist-info/LICENSE
pytest_django_factories-0.2.3.dist-info/METADATA
pytest_django_factories-0.2.3.dist-info/WHEEL
pytest_django_factories-0.2.3.dist-info/top_level.txt
pytest_django_factories-0.2.3.dist-info/RECORD
