Metadata-Version: 2.1
Name: pytest-django-factories
Version: 0.2.3
Summary: Factories for your Django models that can be used as Pytest fixtures.
Home-page: http://github.com/jnns/pytest-django-factories
Author: Jannis Vajen
Author-email: jvajen@gmail.com
License: MIT
Platform: UNKNOWN
Classifier: Development Status :: 4 - Beta
Classifier: Framework :: Django
Classifier: Framework :: Pytest
Classifier: Intended Audience :: Developers
Classifier: License :: OSI Approved :: MIT License
Classifier: Programming Language :: Python
Classifier: Programming Language :: Python :: 3
Classifier: Programming Language :: Python :: 3.6
Classifier: Programming Language :: Python :: 3.7
Classifier: Programming Language :: Python :: 3.8
Classifier: Topic :: Software Development :: Libraries :: Python Modules
Classifier: Topic :: Software Development :: Testing
Requires-Python: >=3.6
Requires-Dist: django
